FanBase/FanBase.py
FanBase/__init__.py
FanBase/lib/__init__.py
FanBase/lib/util/__init__.py
FanBase/lib/util/headers.py
FanBase/lib/util/objects.py
fanbase_api-1.0.7.dist-info/LICENSE
fanbase_api-1.0.7.dist-info/METADATA
fanbase_api-1.0.7.dist-info/WHEEL
fanbase_api-1.0.7.dist-info/top_level.txt
fanbase_api-1.0.7.dist-info/RECORD
