Metadata-Version: 2.2
Name: fanbase-api
Version: 1.0.7
Summary: The first fanbase package
Home-page: https://github.com/nfrx1/FanBase
Author: Kapom
Author-email: aasionkj@gmail.com
Classifier: Programming Language :: Python :: 3
Classifier: License :: OSI Approved :: MIT License
Classifier: Operating System :: OS Independent
License-File: LICENSE
Requires-Dist: requests
Dynamic: author
Dynamic: author-email
Dynamic: classifier
Dynamic: description
Dynamic: description-content-type
Dynamic: home-page
Dynamic: requires-dist
Dynamic: summary
